{
"type": "FeatureCollection",
"name": "2a9b2ba1c926_visibility",
"crs": { "type": "name", "properties": { "name": "urn:ogc:def:crs:OGC:1.3:CRS84" } },
"features": [
{ "type": "Feature", "properties": { "visible_points": 5, "total_points": 52, "visibility_pct": 9.6153846153846168 }, "geometry": { "type": "Point", "coordinates": [ -5.103401685507997, 51.778805973917613 ] } },
{ "type": "Feature", "properties": { "visible_points": 7, "total_points": 52, "visibility_pct": 13.461538461538462 }, "geometry": { "type": "Point", "coordinates": [ -5.103201133100661, 51.778811272429628 ] } },
{ "type": "Feature", "properties": { "visible_points": 4, "total_points": 52, "visibility_pct": 7.6923076923076925 }, "geometry": { "type": "Point", "coordinates": [ -5.103000580631712, 51.778816570599716 ] } },
{ "type": "Feature", "properties": { "visible_points": 0, "total_points": 50, "visibility_pct": 0.0 }, "geometry": { "type": "Point", "coordinates": [ -5.102800028101143, 51.778821868427848 ] } },
{ "type": "Feature", "properties": { "visible_points": 2, "total_points": 44, "visibility_pct": 4.5454545454545459 }, "geometry": { "type": "Point", "coordinates": [ -5.102599475508957, 51.778827165914045 ] } },
{ "type": "Feature", "properties": { "visible_points": 0, "total_points": 46, "visibility_pct": 0.0 }, "geometry": { "type": "Point", "coordinates": [ -5.103709910519416, 51.778905759847611 ] } },
{ "type": "Feature", "properties": { "visible_points": 0, "total_points": 52, "visibility_pct": 0.0 }, "geometry": { "type": "Point", "coordinates": [ -5.103509357727744, 51.778911058890927 ] } },
{ "type": "Feature", "properties": { "visible_points": 0, "total_points": 52, "visibility_pct": 0.0 }, "geometry": { "type": "Point", "coordinates": [ -5.103308804874443, 51.778916357592315 ] } },
{ "type": "Feature", "properties": { "visible_points": 0, "total_points": 52, "visibility_pct": 0.0 }, "geometry": { "type": "Point", "coordinates": [ -5.103108251959517, 51.778921655951734 ] } },
{ "type": "Feature", "properties": { "visible_points": 0, "total_points": 52, "visibility_pct": 0.0 }, "geometry": { "type": "Point", "coordinates": [ -5.10290769898297, 51.778926953969226 ] } },
{ "type": "Feature", "properties": { "visible_points": 1, "total_points": 48, "visibility_pct": 2.083333333333333 }, "geometry": { "type": "Point", "coordinates": [ -5.102707145944805, 51.778932251644761 ] } },
{ "type": "Feature", "properties": { "visible_points": 2, "total_points": 52, "visibility_pct": 3.8461538461538463 }, "geometry": { "type": "Point", "coordinates": [ -5.103416477155819, 51.779021442648535 ] } },
{ "type": "Feature", "properties": { "visible_points": 3, "total_points": 52, "visibility_pct": 5.7692307692307692 }, "geometry": { "type": "Point", "coordinates": [ -5.103215923794918, 51.779026741197313 ] } },
{ "type": "Feature", "properties": { "visible_points": 0, "total_points": 52, "visibility_pct": 0.0 }, "geometry": { "type": "Point", "coordinates": [ -5.103015370372392, 51.779032039404157 ] } },
{ "type": "Feature", "properties": { "visible_points": 1, "total_points": 49, "visibility_pct": 2.0408163265306123 }, "geometry": { "type": "Point", "coordinates": [ -5.102814816888245, 51.779037337269038 ] } },
{ "type": "Feature", "properties": { "visible_points": 2, "total_points": 52, "visibility_pct": 3.8461538461538463 }, "geometry": { "type": "Point", "coordinates": [ -5.103323596137915, 51.779131826336425 ] } },
{ "type": "Feature", "properties": { "visible_points": 3, "total_points": 52, "visibility_pct": 5.7692307692307692 }, "geometry": { "type": "Point", "coordinates": [ -5.103123042269416, 51.779137124732628 ] } },
{ "type": "Feature", "properties": { "visible_points": 2, "total_points": 50, "visibility_pct": 4.0 }, "geometry": { "type": "Point", "coordinates": [ -5.102922488339285, 51.779142422786869 ] } },
{ "type": "Feature", "properties": { "visible_points": 2, "total_points": 51, "visibility_pct": 3.9215686274509802 }, "geometry": { "type": "Point", "coordinates": [ -5.103230714674036, 51.77924220995466 ] } },
{ "type": "Feature", "properties": { "visible_points": 6, "total_points": 50, "visibility_pct": 12.0 }, "geometry": { "type": "Point", "coordinates": [ -5.10303016029793, 51.779247508198239 ] } },
{ "type": "Feature", "properties": { "visible_points": 1, "total_points": 46, "visibility_pct": 2.1739130434782608 }, "geometry": { "type": "Point", "coordinates": [ -5.102829605860194, 51.779252806099883 ] } }
]
}
