{
"type": "FeatureCollection",
"name": "ca012f91e62b_visibility",
"crs": { "type": "name", "properties": { "name": "urn:ogc:def:crs:OGC:1.3:CRS84" } },
"features": [
{ "type": "Feature", "properties": { "visible_points": 0, "total_points": 44, "visibility_pct": 0.0 }, "geometry": { "type": "Point", "coordinates": [ -4.396068307827568, 52.040311814605417 ] } },
{ "type": "Feature", "properties": { "visible_points": 2, "total_points": 49, "visibility_pct": 4.0816326530612246 }, "geometry": { "type": "Point", "coordinates": [ -4.395866466122026, 52.040315920396324 ] } },
{ "type": "Feature", "properties": { "visible_points": 4, "total_points": 54, "visibility_pct": 7.4074074074074066 }, "geometry": { "type": "Point", "coordinates": [ -4.395664624368089, 52.040320025841766 ] } },
{ "type": "Feature", "properties": { "visible_points": 0, "total_points": 48, "visibility_pct": 0.0 }, "geometry": { "type": "Point", "coordinates": [ -4.395973151948565, 52.040421662878714 ] } },
{ "type": "Feature", "properties": { "visible_points": 0, "total_points": 53, "visibility_pct": 0.0 }, "geometry": { "type": "Point", "coordinates": [ -4.395771309732367, 52.04042576851316 ] } },
{ "type": "Feature", "properties": { "visible_points": 2, "total_points": 58, "visibility_pct": 3.4482758620689653 }, "geometry": { "type": "Point", "coordinates": [ -4.395569467467785, 52.040429873802111 ] } },
{ "type": "Feature", "properties": { "visible_points": 6, "total_points": 62, "visibility_pct": 9.67741935483871 }, "geometry": { "type": "Point", "coordinates": [ -4.39536762515481, 52.040433978745554 ] } },
{ "type": "Feature", "properties": { "visible_points": 1, "total_points": 64, "visibility_pct": 1.5625 }, "geometry": { "type": "Point", "coordinates": [ -4.395165782793456, 52.04043808334351 ] } },
{ "type": "Feature", "properties": { "visible_points": 0, "total_points": 52, "visibility_pct": 0.0 }, "geometry": { "type": "Point", "coordinates": [ -4.395877995607299, 52.040531511079465 ] } },
{ "type": "Feature", "properties": { "visible_points": 0, "total_points": 57, "visibility_pct": 0.0 }, "geometry": { "type": "Point", "coordinates": [ -4.39567615288045, 52.04053561655742 ] } },
{ "type": "Feature", "properties": { "visible_points": 0, "total_points": 61, "visibility_pct": 0.0 }, "geometry": { "type": "Point", "coordinates": [ -4.395474310105206, 52.040539721689882 ] } },
{ "type": "Feature", "properties": { "visible_points": 3, "total_points": 64, "visibility_pct": 4.6875 }, "geometry": { "type": "Point", "coordinates": [ -4.395272467281582, 52.040543826476814 ] } },
{ "type": "Feature", "properties": { "visible_points": 3, "total_points": 60, "visibility_pct": 5.0 }, "geometry": { "type": "Point", "coordinates": [ -4.395070624409575, 52.040547930918279 ] } },
{ "type": "Feature", "properties": { "visible_points": 0, "total_points": 52, "visibility_pct": 0.0 }, "geometry": { "type": "Point", "coordinates": [ -4.39486878148919, 52.04055203501423 ] } },
{ "type": "Feature", "properties": { "visible_points": 0, "total_points": 49, "visibility_pct": 0.0 }, "geometry": { "type": "Point", "coordinates": [ -4.395984681992885, 52.040637253540666 ] } },
{ "type": "Feature", "properties": { "visible_points": 0, "total_points": 55, "visibility_pct": 0.0 }, "geometry": { "type": "Point", "coordinates": [ -4.395782838803768, 52.040641359207633 ] } },
{ "type": "Feature", "properties": { "visible_points": 1, "total_points": 60, "visibility_pct": 1.6666666666666667 }, "geometry": { "type": "Point", "coordinates": [ -4.395580995566254, 52.040645464529092 ] } },
{ "type": "Feature", "properties": { "visible_points": 0, "total_points": 64, "visibility_pct": 0.0 }, "geometry": { "type": "Point", "coordinates": [ -4.395379152280353, 52.040649569505064 ] } },
{ "type": "Feature", "properties": { "visible_points": 0, "total_points": 61, "visibility_pct": 0.0 }, "geometry": { "type": "Point", "coordinates": [ -4.395177308946072, 52.04065367413552 ] } },
{ "type": "Feature", "properties": { "visible_points": 0, "total_points": 55, "visibility_pct": 0.0 }, "geometry": { "type": "Point", "coordinates": [ -4.394975465563414, 52.040657778420488 ] } },
{ "type": "Feature", "properties": { "visible_points": 3, "total_points": 47, "visibility_pct": 6.3829787234042552 }, "geometry": { "type": "Point", "coordinates": [ -4.394773622132378, 52.040661882359942 ] } },
{ "type": "Feature", "properties": { "visible_points": 2, "total_points": 40, "visibility_pct": 5.0 }, "geometry": { "type": "Point", "coordinates": [ -4.394571778652977, 52.040665985953908 ] } },
{ "type": "Feature", "properties": { "visible_points": 1, "total_points": 42, "visibility_pct": 2.3809523809523809 }, "geometry": { "type": "Point", "coordinates": [ -4.394678462313284, 52.040771729633093 ] } },
{ "type": "Feature", "properties": { "visible_points": 0, "total_points": 35, "visibility_pct": 0.0 }, "geometry": { "type": "Point", "coordinates": [ -4.394476618323224, 52.040775833070548 ] } }
]
}
