{
"type": "FeatureCollection",
"name": "CERED_81_toilets",
"crs": { "type": "name", "properties": { "name": "urn:ogc:def:crs:OGC:1.3:CRS84" } },
"features": [
{ "type": "Feature", "properties": { "name": "Unknown", "payment_info": "Free", "accessible": "True", "radar": "False", "women": "True", "men": "True", "baby_change": "True", "Mon": "00:00-00:00", "Tue": "00:00-00:00", "Wed": "00:00-00:00", "Thu": "00:00-00:00", "Fri": "00:00-00:00", "Sat": "00:00-00:00", "Sun": "00:00-00:00", "index_right": 61, "park_offical_id": "CERED_81" }, "geometry": { "type": "Point", "coordinates": [ -4.064716101, 52.417914943 ] } },
{ "type": "Feature", "properties": { "name": "National Library of Wales", "payment_info": "Free", "accessible": "False", "radar": "Unknown", "women": "True", "men": "True", "baby_change": "Unknown", "Mon": "09:00-17:00", "Tue": "09:00-17:00", "Wed": "09:00-17:00", "Thu": "09:00-17:00", "Fri": "09:00-17:00", "Sat": "Closed", "Sun": "Closed", "index_right": 61, "park_offical_id": "CERED_81" }, "geometry": { "type": "Point", "coordinates": [ -4.068374634, 52.414520377 ] } },
{ "type": "Feature", "properties": { "name": "Students Union", "payment_info": "Free", "accessible": "False", "radar": "Unknown", "women": "Unknown", "men": "Unknown", "baby_change": "Unknown", "Mon": "09:00-17:00", "Tue": "09:00-17:00", "Wed": "09:00-17:00", "Thu": "09:00-17:00", "Fri": "09:00-17:00", "Sat": "09:00-17:00", "Sun": "09:00-17:00", "index_right": 61, "park_offical_id": "CERED_81" }, "geometry": { "type": "Point", "coordinates": [ -4.062935114, 52.415323645 ] } },
{ "type": "Feature", "properties": { "name": "Arts Centre", "payment_info": "Free", "accessible": "False", "radar": "Unknown", "women": "True", "men": "True", "baby_change": "Unknown", "Mon": "Unknown", "Tue": "Unknown", "Wed": "Unknown", "Thu": "Unknown", "Fri": "Unknown", "Sat": "Unknown", "Sun": "Unknown", "index_right": 61, "park_offical_id": "CERED_81" }, "geometry": { "type": "Point", "coordinates": [ -4.062951207, 52.415781714 ] } }
]
}
