{
"type": "FeatureCollection",
"name": "CARMA_62_toilets",
"crs": { "type": "name", "properties": { "name": "urn:ogc:def:crs:OGC:1.3:CRS84" } },
"features": [
{ "type": "Feature", "properties": { "name": "Llanelli Station", "payment_info": "Free", "accessible": "False", "radar": "False", "women": "Unknown", "men": "Unknown", "baby_change": "False", "Mon": "Unknown", "Tue": "Unknown", "Wed": "Unknown", "Thu": "Unknown", "Fri": "Unknown", "Sat": "Unknown", "Sun": "Unknown", "index_right": 156, "park_offical_id": "CARMA_62" }, "geometry": { "type": "Point", "coordinates": [ -4.161325167, 51.673866715 ] } }
]
}
