{
"type": "FeatureCollection",
"name": "cc6ca70cf872_visibility",
"crs": { "type": "name", "properties": { "name": "urn:ogc:def:crs:OGC:1.3:CRS84" } },
"features": [
{ "type": "Feature", "properties": { "visible_points": 0, "total_points": 56, "visibility_pct": 0.0 }, "geometry": { "type": "Point", "coordinates": [ -4.182691100800734, 53.171176820350134 ] } },
{ "type": "Feature", "properties": { "visible_points": 0, "total_points": 55, "visibility_pct": 0.0 }, "geometry": { "type": "Point", "coordinates": [ -4.182483963898719, 53.17118061676878 ] } },
{ "type": "Feature", "properties": { "visible_points": 0, "total_points": 56, "visibility_pct": 0.0 }, "geometry": { "type": "Point", "coordinates": [ -4.183007279541182, 53.17127891264257 ] } },
{ "type": "Feature", "properties": { "visible_points": 0, "total_points": 56, "visibility_pct": 0.0 }, "geometry": { "type": "Point", "coordinates": [ -4.182800142193217, 53.171282709616136 ] } },
{ "type": "Feature", "properties": { "visible_points": 0, "total_points": 56, "visibility_pct": 0.0 }, "geometry": { "type": "Point", "coordinates": [ -4.182593004798583, 53.171286506229706 ] } },
{ "type": "Feature", "properties": { "visible_points": 0, "total_points": 55, "visibility_pct": 0.0 }, "geometry": { "type": "Point", "coordinates": [ -4.182385867357276, 53.171290302483243 ] } },
{ "type": "Feature", "properties": { "visible_points": 0, "total_points": 55, "visibility_pct": 0.0 }, "geometry": { "type": "Point", "coordinates": [ -4.183116321965576, 53.17138480160633 ] } },
{ "type": "Feature", "properties": { "visible_points": 3, "total_points": 56, "visibility_pct": 5.3571428571428568 }, "geometry": { "type": "Point", "coordinates": [ -4.18290918412499, 53.171388598774854 ] } },
{ "type": "Feature", "properties": { "visible_points": 3, "total_points": 56, "visibility_pct": 5.3571428571428568 }, "geometry": { "type": "Point", "coordinates": [ -4.182702046237729, 53.171392395583354 ] } },
{ "type": "Feature", "properties": { "visible_points": 0, "total_points": 56, "visibility_pct": 0.0 }, "geometry": { "type": "Point", "coordinates": [ -4.182494908303792, 53.171396192031843 ] } },
{ "type": "Feature", "properties": { "visible_points": 0, "total_points": 54, "visibility_pct": 0.0 }, "geometry": { "type": "Point", "coordinates": [ -4.182287770323196, 53.171399988120314 ] } },
{ "type": "Feature", "properties": { "visible_points": 0, "total_points": 48, "visibility_pct": 0.0 }, "geometry": { "type": "Point", "coordinates": [ -4.182080632295934, 53.171403783848795 ] } },
{ "type": "Feature", "properties": { "visible_points": 0, "total_points": 50, "visibility_pct": 0.0 }, "geometry": { "type": "Point", "coordinates": [ -4.183225364929264, 53.171490690462832 ] } },
{ "type": "Feature", "properties": { "visible_points": 0, "total_points": 56, "visibility_pct": 0.0 }, "geometry": { "type": "Point", "coordinates": [ -4.183018226596051, 53.171494487826266 ] } },
{ "type": "Feature", "properties": { "visible_points": 3, "total_points": 56, "visibility_pct": 5.3571428571428568 }, "geometry": { "type": "Point", "coordinates": [ -4.18281108821616, 53.17149828482971 ] } },
{ "type": "Feature", "properties": { "visible_points": 2, "total_points": 56, "visibility_pct": 3.5714285714285712 }, "geometry": { "type": "Point", "coordinates": [ -4.182603949789603, 53.171502081473143 ] } },
{ "type": "Feature", "properties": { "visible_points": 0, "total_points": 56, "visibility_pct": 0.0 }, "geometry": { "type": "Point", "coordinates": [ -4.182396811316366, 53.171505877756552 ] } },
{ "type": "Feature", "properties": { "visible_points": 0, "total_points": 51, "visibility_pct": 0.0 }, "geometry": { "type": "Point", "coordinates": [ -4.182189672796476, 53.171509673679964 ] } },
{ "type": "Feature", "properties": { "visible_points": 0, "total_points": 55, "visibility_pct": 0.0 }, "geometry": { "type": "Point", "coordinates": [ -4.182920130733889, 53.171604173968774 ] } },
{ "type": "Feature", "properties": { "visible_points": 2, "total_points": 56, "visibility_pct": 3.5714285714285712 }, "geometry": { "type": "Point", "coordinates": [ -4.1827129918147, 53.171607970807145 ] } },
{ "type": "Feature", "properties": { "visible_points": 0, "total_points": 56, "visibility_pct": 0.0 }, "geometry": { "type": "Point", "coordinates": [ -4.182505852848834, 53.171611767285505 ] } },
{ "type": "Feature", "properties": { "visible_points": 2, "total_points": 53, "visibility_pct": 3.7735849056603774 }, "geometry": { "type": "Point", "coordinates": [ -4.182614894920591, 53.171717656707166 ] } }
]
}
