{
"type": "FeatureCollection",
"name": "CERED_205",
"crs": { "type": "name", "properties": { "name": "urn:ogc:def:crs:OGC:1.3:CRS84" } },
"features": [
{ "type": "Feature", "properties": { "osm_id": 11564097599, "name": "Bench in Mariamne's Garden", "amenity": "bench", "man_made": null, "leisure": null, "playground": null, "memorial": null }, "geometry": { "type": "Point", "coordinates": [ -3.8158707, 52.3428264 ] } }
]
}
