{
"type": "FeatureCollection",
"name": "CERED_30",
"crs": { "type": "name", "properties": { "name": "urn:ogc:def:crs:OGC:1.3:CRS84" } },
"features": [
{ "type": "Feature", "properties": { "osm_id": 9367615449, "name": null, "amenity": null, "man_made": null, "leisure": "picnic_table", "playground": null, "memorial": null }, "geometry": { "type": "Point", "coordinates": [ -4.3094032, 52.0395563 ] } },
{ "type": "Feature", "properties": { "osm_id": 9367615450, "name": null, "amenity": null, "man_made": null, "leisure": "picnic_table", "playground": null, "memorial": null }, "geometry": { "type": "Point", "coordinates": [ -4.3093094, 52.0395864 ] } },
{ "type": "Feature", "properties": { "osm_id": 9367615451, "name": null, "amenity": null, "man_made": null, "leisure": "picnic_table", "playground": null, "memorial": null }, "geometry": { "type": "Point", "coordinates": [ -4.309194, 52.0396107 ] } },
{ "type": "Feature", "properties": { "osm_id": 9367615448, "name": null, "amenity": null, "man_made": null, "leisure": "picnic_table", "playground": null, "memorial": null }, "geometry": { "type": "Point", "coordinates": [ -4.3094676, 52.0396482 ] } },
{ "type": "Feature", "properties": { "osm_id": 9367615452, "name": null, "amenity": null, "man_made": null, "leisure": "picnic_table", "playground": null, "memorial": null }, "geometry": { "type": "Point", "coordinates": [ -4.3091545, 52.0397707 ] } }
]
}
