{
"type": "FeatureCollection",
"name": "POWYS_156",
"crs": { "type": "name", "properties": { "name": "urn:ogc:def:crs:OGC:1.3:CRS84" } },
"features": [
{ "type": "Feature", "properties": { "osm_id": 3957259869, "name": null, "amenity": "bench", "man_made": null, "leisure": null, "playground": null, "memorial": null }, "geometry": { "type": "Point", "coordinates": [ -3.3125863, 52.5138497 ] } },
{ "type": "Feature", "properties": { "osm_id": 3957259874, "name": null, "amenity": "bench", "man_made": null, "leisure": null, "playground": null, "memorial": null }, "geometry": { "type": "Point", "coordinates": [ -3.3122686, 52.5138654 ] } },
{ "type": "Feature", "properties": { "osm_id": 3957259876, "name": null, "amenity": "bench", "man_made": null, "leisure": null, "playground": null, "memorial": null }, "geometry": { "type": "Point", "coordinates": [ -3.3123311, 52.5138692 ] } }
]
}
