{
"type": "FeatureCollection",
"name": "CARMA_561",
"crs": { "type": "name", "properties": { "name": "urn:ogc:def:crs:OGC:1.3:CRS84" } },
"features": [
{ "type": "Feature", "properties": { "osm_id": 10119780255, "name": null, "amenity": null, "man_made": null, "leisure": "picnic_table", "playground": null, "memorial": null }, "geometry": { "type": "Point", "coordinates": [ -4.5909852, 51.8778349 ] } },
{ "type": "Feature", "properties": { "osm_id": 10119780254, "name": null, "amenity": null, "man_made": null, "leisure": "picnic_table", "playground": null, "memorial": null }, "geometry": { "type": "Point", "coordinates": [ -4.5909188, 51.8779208 ] } },
{ "type": "Feature", "properties": { "osm_id": 10119780253, "name": null, "amenity": null, "man_made": null, "leisure": "picnic_table", "playground": null, "memorial": null }, "geometry": { "type": "Point", "coordinates": [ -4.5907164, 51.8779228 ] } },
{ "type": "Feature", "properties": { "osm_id": 10119780252, "name": null, "amenity": null, "man_made": null, "leisure": "picnic_table", "playground": null, "memorial": null }, "geometry": { "type": "Point", "coordinates": [ -4.591001, 51.8780009 ] } }
]
}
