{
"type": "FeatureCollection",
"name": "CARMA_64",
"crs": { "type": "name", "properties": { "name": "urn:ogc:def:crs:OGC:1.3:CRS84" } },
"features": [
{ "type": "Feature", "properties": { "osm_id": 4297049201, "name": null, "amenity": "bench", "man_made": null, "leisure": null, "playground": null, "memorial": null }, "geometry": { "type": "Point", "coordinates": [ -4.1535521, 51.6703528 ] } },
{ "type": "Feature", "properties": { "osm_id": 4297049190, "name": null, "amenity": "bench", "man_made": null, "leisure": null, "playground": null, "memorial": null }, "geometry": { "type": "Point", "coordinates": [ -4.1535279, 51.6703961 ] } },
{ "type": "Feature", "properties": { "osm_id": 4297048082, "name": null, "amenity": "bench", "man_made": null, "leisure": null, "playground": null, "memorial": null }, "geometry": { "type": "Point", "coordinates": [ -4.1536004, 51.6704085 ] } }
]
}
