{
"type": "FeatureCollection",
"name": "CARMA_595",
"crs": { "type": "name", "properties": { "name": "urn:ogc:def:crs:OGC:1.3:CRS84" } },
"features": [
{ "type": "Feature", "properties": { "osm_id": 12819254617, "name": null, "amenity": "bench", "man_made": null, "leisure": null, "playground": null, "memorial": null }, "geometry": { "type": "Point", "coordinates": [ -4.6941632, 51.6723652 ] } },
{ "type": "Feature", "properties": { "osm_id": 12819254616, "name": null, "amenity": "bench", "man_made": null, "leisure": null, "playground": null, "memorial": null }, "geometry": { "type": "Point", "coordinates": [ -4.693819, 51.6724681 ] } },
{ "type": "Feature", "properties": { "osm_id": 12819254621, "name": null, "amenity": "bench", "man_made": null, "leisure": null, "playground": null, "memorial": null }, "geometry": { "type": "Point", "coordinates": [ -4.6939604, 51.6725508 ] } }
]
}
