{
"type": "FeatureCollection",
"name": "CARMA_56",
"crs": { "type": "name", "properties": { "name": "urn:ogc:def:crs:OGC:1.3:CRS84" } },
"features": [
{ "type": "Feature", "properties": { "osm_id": 3579382459, "name": null, "amenity": "bench", "man_made": null, "leisure": null, "playground": null, "memorial": null }, "geometry": { "type": "Point", "coordinates": [ -4.1271421, 51.6920518 ] } },
{ "type": "Feature", "properties": { "osm_id": 3579382461, "name": null, "amenity": "bench", "man_made": null, "leisure": null, "playground": null, "memorial": null }, "geometry": { "type": "Point", "coordinates": [ -4.1276575, 51.6924092 ] } }
]
}
