{
"type": "FeatureCollection",
"name": "GWYNE_493",
"crs": { "type": "name", "properties": { "name": "urn:ogc:def:crs:OGC:1.3:CRS84" } },
"features": [
{ "type": "Feature", "properties": { "osm_id": 13777418864, "name": null, "amenity": "bench", "man_made": null, "leisure": null, "playground": null, "memorial": null }, "geometry": { "type": "Point", "coordinates": [ -4.4822741, 52.8555837 ] } },
{ "type": "Feature", "properties": { "osm_id": 13777418863, "name": null, "amenity": "bench", "man_made": null, "leisure": null, "playground": null, "memorial": null }, "geometry": { "type": "Point", "coordinates": [ -4.4822875, 52.8556279 ] } },
{ "type": "Feature", "properties": { "osm_id": 11202129292, "name": null, "amenity": "bench", "man_made": null, "leisure": null, "playground": null, "memorial": null }, "geometry": { "type": "Point", "coordinates": [ -4.4822988, 52.8556636 ] } }
]
}
